etool/__init__.py
etool/file_io.py
etool/metrics.py
easytool-0.1.7.dist-info/METADATA
easytool-0.1.7.dist-info/WHEEL
easytool-0.1.7.dist-info/top_level.txt
easytool-0.1.7.dist-info/RECORD
