Metadata-Version: 2.1
Name: easytool
Version: 0.1.7
Summary: 常用工具函数
Author: Yu Zecheng
Requires-Python: >=3.0
